lumberjackth/models/taskcluster.py
lumberjackth/models/core.py
lumberjackth/models/performance.py
lumberjackth/models/__init__.py
lumberjackth/cli.py
lumberjackth/exceptions.py
lumberjackth/client.py
lumberjackth/__init__.py
lumberjackth-1.3.0.dist-info/WHEEL
lumberjackth-1.3.0.dist-info/entry_points.txt
lumberjackth-1.3.0.dist-info/METADATA
lumberjackth-1.3.0.dist-info/RECORD
