Metadata-Version: 2.4
Name: lumberjackth
Version: 1.3.0
Summary: A modern CLI and Python client for Mozilla Treeherder
Keywords: mozilla,treeherder,ci,testing,firefox
Author: Jonathan Moss
Author-email: Jonathan Moss <jmoss@mozilla.com>
License-Expression: MPL-2.0
Classifier: Development Status :: 4 - Beta
Classifier: Environment :: Console
Classifier: Intended Audience :: Developers
Classifier: License :: OSI Approved :: Mozilla Public License 2.0 (MPL 2.0)
Classifier: Operating System :: OS Independent
Classifier: Programming Language :: Python :: 3
Classifier: Programming Language :: Python :: 3.11
Classifier: Programming Language :: Python :: 3.12
Classifier: Programming Language :: Python :: 3.13
Classifier: Programming Language :: Python :: 3.14
Classifier: Topic :: Software Development :: Testing
Requires-Dist: click>=8.3.1
Requires-Dist: httpx>=0.28.1
Requires-Dist: pydantic>=2.12.5
Requires-Dist: rich>=14.3.1
Requires-Python: >=3.11
Project-URL: Documentation, https://github.com/jwmossmoz/lumberjackth#readme
Project-URL: Homepage, https://github.com/jwmossmoz/lumberjackth
Project-URL: Issues, https://github.com/jwmossmoz/lumberjackth/issues
Project-URL: Repository, https://github.com/jwmossmoz/lumberjackth
